fpvs/__init__.py
fpvs/__version__.py
fpvs/scmversion.py
fpvs/scripts/__init__.py
fpvs/scripts/scan.py
fpvs-0.3.0.dist-info/LICENSE
fpvs-0.3.0.dist-info/METADATA
fpvs-0.3.0.dist-info/WHEEL
fpvs-0.3.0.dist-info/entry_points.txt
fpvs-0.3.0.dist-info/top_level.txt
fpvs-0.3.0.dist-info/RECORD
