Metadata-Version: 2.1
Name: fpvs
Version: 0.3.0
Summary: Fast Python Vulnerability Scanner
Home-page: UNKNOWN
Author: Klaas van Schelven
License: BSD-3-Clause
Project-URL: Github, https://github.com/vanschelven/fpvs/
Platform: UNKNOWN
Classifier: Development Status :: 4 - Beta
Classifier: Environment :: Console
Classifier: Intended Audience :: Developers
Classifier: License :: OSI Approved :: BSD License
Classifier: Operating System :: POSIX
Classifier: Programming Language :: Python
Requires-Python: >=3.7.*
License-File: LICENSE
Requires-Dist: packaging
Requires-Dist: pyyaml
Requires-Dist: wheel-filename
